pythonclientlib4platform-1.0.2-py3.11-nspkg.pth
lib4platform/apimanager/__init__.py
lib4platform/apimanager/apimanagerclient.py
lib4platform/base/__init__.py
lib4platform/base/client.py
lib4platform/common/__init__.py
lib4platform/common/config.py
lib4platform/common/log.py
lib4platform/common/utils.py
lib4platform/enum/__init__.py
lib4platform/enum/querytype.py
lib4platform/enum/resprotocols.py
lib4platform/enum/restheaders.py
lib4platform/enum/restmethods.py
lib4platform/files/__init__.py
lib4platform/files/filemanager.py
lib4platform/files/filemanager_test.py
lib4platform/iotbroker/__init__.py
lib4platform/iotbroker/digitalclient.py
lib4platform/iotbroker/digitalclient_test.py
lib4platform/microservice/__init__.py
lib4platform/microservice/modelserviceclient.py
lib4platform/mqttclient/__init__.py
lib4platform/mqttclient/core.py
lib4platform/mqttclient/utils.py
pythonclientlib4platform-1.0.2.dist-info/licenses/LICENSE
pythonclientlib4platform-1.0.2.dist-info/METADATA
pythonclientlib4platform-1.0.2.dist-info/WHEEL
pythonclientlib4platform-1.0.2.dist-info/namespace_packages.txt
pythonclientlib4platform-1.0.2.dist-info/top_level.txt
pythonclientlib4platform-1.0.2.dist-info/RECORD
