Metadata-Version: 2.4
Name: pythonclientlib4platform
Version: 1.0.2
Summary: Python Implementation of the Platform utilities
Home-page: 
License: Apache v2.0
Keywords: Platform client services
License-File: LICENSE
Requires-Dist: paho-mqtt
Requires-Dist: six
Requires-Dist: requests
Dynamic: description
Dynamic: description-content-type
Dynamic: keywords
Dynamic: license
Dynamic: license-file
Dynamic: requires-dist
Dynamic: summary
